LoopProjectFile/DataCollection.py
LoopProjectFile/Extents.py
LoopProjectFile/ExtractedInformation.py
LoopProjectFile/GeophysicalModels.py
LoopProjectFile/LoopProjectFile.py
LoopProjectFile/LoopProjectFileUtils.py
LoopProjectFile/Permutations.py
LoopProjectFile/ProbabilityModels.py
LoopProjectFile/StructuralModels.py
LoopProjectFile/Version.py
LoopProjectFile/__init__.py
LoopProjectFile/projectfile.py
LoopProjectFile-0.1.4.dist-info/LICENSE
LoopProjectFile-0.1.4.dist-info/METADATA
LoopProjectFile-0.1.4.dist-info/WHEEL
LoopProjectFile-0.1.4.dist-info/top_level.txt
LoopProjectFile-0.1.4.dist-info/RECORD
