Metadata-Version: 2.1
Name: LoopProjectFile
Version: 0.1.4
Summary: Open source structural geology data storage for Loop Projects
Author-email: Roy Thomson <roy.thomson@monash.edu>
License: MIT
Project-URL: Documentation, https://Loop3d.org/LoopProjectFile/
Project-URL: Bug Tracker, https://github.com/loop3d/LoopProjectFile/issues
Project-URL: Source Code, https://github.com/loop3d/LoopProjectFile
Keywords: earth sciences,data storage,structural geology,geology,loop3d
Classifier: Development Status :: 5 - Production/Stable
Classifier: Intended Audience :: Science/Research
Classifier: Topic :: Scientific/Engineering :: Information Analysis
Classifier: License :: OSI Approved :: MIT License
Classifier: Operating System :: Microsoft :: Windows
Classifier: Operating System :: POSIX
Classifier: Operating System :: MacOS
Classifier: Programming Language :: Python :: 3.8
Classifier: Programming Language :: Python :: 3.9
Classifier: Programming Language :: Python :: 3.10
Classifier: Programming Language :: Python :: 3.11
Classifier: Programming Language :: Python :: 3.12
Requires-Python: >=3.8
License-File: LICENSE
Requires-Dist: numpy
Requires-Dist: pandas
Requires-Dist: netCDF4
